{
	"next_topic_id": 2,
	"topic": [
		{
			"topic_id": 1569202528,
			"title": "谷歌宣布实现 量子霸权",
			"body": "“量子霸权”是指量子计算拥有的超越所有经典计算机的计算能力。如能实现，这将是量子计算领域的重大里程碑，但此前从未有研发者实现这一目标。近日，据多家外媒报道，谷歌的一份研究报告显示，他们已经实现了“量子霸权”：全球最大的传统超级计算机Summit要用1万年解决的问题，其量子计算机在3分20秒内就能算出。谷歌一度将相关论文上传至NASA官网上，但随后不久，该论文被删除。对此，NASA和谷歌均未作出回应。",
			"added": 1569202527,
			"parent_topic_uri": "1517728147_1K7tW4WEbso38uMs4RN3W7GihA6tTqrApz"
		}
	],
	"topic_vote": {},
	"next_comment_id": 3,
	"comment": {
		"1569155400_13t3sJJF35Eei5GApCSAVFp65aZjjZB5jE": [
			{
				"comment_id": 1,
				"body": "我个人也是喜欢可爱娇羞类型，期待...",
				"added": 1569215247
			},
			{
				"comment_id": 2,
				"body": "> [rero@zeroid.bit](#comment_1_13t3sJJF35Eei5GApCSAVFp65aZjjZB5jE): 谢谢评论。有个问题请教一下。zerom [...]\n\n这个问题，我了解些。hub只能加入一个，但也能看到其他hub用户的发言，如果你关注了的话。有个站点可以一键关注全部hub，你可以在网站大全中找一下。",
				"added": 1569215535
			}
		]
	},
	"comment_vote": {}
}