{
	"next_topic_id": 1,
	"topic": [],
	"topic_vote": {},
	"next_comment_id": 5,
	"comment": {
		"306_157kFKiaEbRUds2HCBUpv33t4Unezi6dR6": [
			{
				"comment_id": 1,
				"body": "话说，零网有网文站么？",
				"added": 1533724107
			}
		],
		"1_1JRYCe7ZmABZF7Bak4tA9QzdYoY8z1t1oY": [
			{
				"comment_id": 2,
				"body": "嘴上喊着反送中，结果一周几次返深圳自动送中。",
				"added": 1564654015
			},
			{
				"comment_id": 3,
				"body": "> [wwwyes](#comment_5_1JRYCe7ZmABZF7Bak4tA9QzdYoY8z1t1oY): 你对<反送中>的理解肤浅了。 [...]\n\n“肤浅”？\n一个在香港都疑神疑鬼担心被抓的人居然可以心安的跑深圳，这是什么逻辑。\n我觉得这几天自己剪回乡证的人倒是遵循他的立场。其他人，呵呵。",
				"added": 1564914346
			},
			{
				"comment_id": 4,
				"body": "> [wwwyes](#comment_6_1JRYCe7ZmABZF7Bak4tA9QzdYoY8z1t1oY): 黑字写着50年不\n\n请问一国两制哪里变了？\n你是指23条一直没立法么？导致现阶段出现有危害一国的行为不能严惩。\n另外，自动送中的笑话可不是什么“深圳”人，某果日报还说的是要查DNA呢。",
				"added": 1565240144
			}
		]
	},
	"comment_vote": {}
}