{
	"message": [
		{
			"body": "test",
			"date_added": 1456400664969
		},
		{
			"body": "dfdsfdsfd",
			"date_added": 1456400706829
		},
		{
			"body": "testtesttest",
			"date_added": 1456400747028
		},
		{
			"body": "dsafdsafds",
			"date_added": 1456401845930
		},
		{
			"body": "fdsafdsafd",
			"date_added": 1456401848262
		},
		{
			"body": "fdsafdsfd",
			"date_added": 1456401850322
		},
		{
			"body": "dsafdsfads",
			"date_added": 1456401852190
		},
		{
			"body": "123234",
			"date_added": 1456401878862
		},
		{
			"body": "dsafds",
			"date_added": 1456402255144
		},
		{
			"body": "xxxx",
			"date_added": 1456402264161
		},
		{
			"body": "dtestet",
			"date_added": 1456402271079
		},
		{
			"body": "dsafdsafd",
			"date_added": 1456402450807
		},
		{
			"body": "dsafdsafd",
			"date_added": 1456402452071
		},
		{
			"body": "dsafdsafd",
			"date_added": 1456402452438
		},
		{
			"body": "dsafdsafd",
			"date_added": 1456402452647
		},
		{
			"body": "dsafdsafdfdsafds",
			"date_added": 1456402453808
		},
		{
			"body": "dsafdsafdfdsafds",
			"date_added": 1456402454015
		},
		{
			"body": "dsafdsafdfdsafds",
			"date_added": 1456402454174
		},
		{
			"body": "dsafds",
			"date_added": 1456402544383
		},
		{
			"body": "xxxx",
			"date_added": 1456402556327
		},
		{
			"body": "cccc",
			"date_added": 1456402560407
		},
		{
			"body": "http://127.0.0.1:43110/16yppFb5mFpvynYXrGHVVxSLUkQePX556z",
			"date_added": 1456402595562
		},
		{
			"body": "ztzz",
			"date_added": 1456403522969
		},
		{
			"body": "test maggie",
			"date_added": 1456421955343
		},
		{
			"body": ":)",
			"date_added": 1456429948097
		},
		{
			"body": "y i dont see maggie1????",
			"date_added": 1456431053636
		},
		{
			"body": "test",
			"date_added": 1456431422965
		},
		{
			"body": "now I can see maggie1 cool!",
			"date_added": 1456432114943
		},
		{
			"body": "moin",
			"date_added": 1456741116728
		},
		{
			"body": "good",
			"date_added": 1456742431927
		},
		{
			"body": "0",
			"date_added": 1456742951682
		},
		{
			"body": "test",
			"date_added": 1456997050785
		},
		{
			"body": "tt",
			"date_added": 1456999624930
		}
	]
}