{
	"next_post_id": 3,
	"next_comment_id": 3,
	"next_follow_id": 4,
	"avatar": "generate",
	"user_name": "Qwertroot1",
	"hub": "1MoonP8t4rk9QamBUPh5Aspkwa1Xhf5ux2",
	"intro": "新 ZeroNet 用户",
	"post": [
		{
			"post_id": 1,
			"date_added": 1557063357,
			"body": "你好 ZeroMe!"
		},
		{
			"post_id": 1557591783,
			"body": "hello test",
			"date_added": 1557591781
		}
	],
	"post_like": {
		"1PDhPG98veiMJCmvfH6Cg6vawYUNWCSzUv_1": 1557063751,
		"1LE5eCnDvvt4GVEK8wHmzFFnf6Tu4SMe2T_1": 1557063786
	},
	"comment": [
		{
			"comment_id": 1,
			"body": "hi",
			"post_uri": "1PDhPG98veiMJCmvfH6Cg6vawYUNWCSzUv_1",
			"date_added": 1557063758
		},
		{
			"comment_id": 2,
			"body": "hi",
			"post_uri": "1LE5eCnDvvt4GVEK8wHmzFFnf6Tu4SMe2T_1",
			"date_added": 1557063794
		}
	],
	"follow": [
		{
			"follow_id": 1,
			"hub": "1MoonP8t4rk9QamBUPh5Aspkwa1Xhf5ux2",
			"auth_address": "1PDhPG98veiMJCmvfH6Cg6vawYUNWCSzUv",
			"user_name": "Uuid1234",
			"date_added": 1557063742
		},
		{
			"follow_id": 2,
			"hub": "1MoonP8t4rk9QamBUPh5Aspkwa1Xhf5ux2",
			"auth_address": "1LE5eCnDvvt4GVEK8wHmzFFnf6Tu4SMe2T",
			"user_name": "864568437",
			"date_added": 1557063788
		},
		{
			"follow_id": 3,
			"hub": "1MX4wgzSR7nCrFshSbGQjA4ixgxGbzrGSX",
			"auth_address": "1B7ZwaaQy8vYGEvCVNiSQMBPhBwVUEqK9r",
			"user_name": "Ask-movie",
			"date_added": 1557276834
		}
	]
}