{
	"next_comment_id": 6,
	"comment": [
		{
			"comment_id": 1,
			"body": "设备名qq33-PC这有我就对了最少做种两天。",
			"post_id": 206,
			"date_added": 1497103988
		},
		{
			"comment_id": 2,
			"body": "设备名qq33-PC这有我就对了最少做种两天。人人为我，我为人人。",
			"post_id": 207,
			"date_added": 1497104903
		},
		{
			"comment_id": 3,
			"body": "qq33-PC批准下",
			"post_id": 210,
			"date_added": 1497269306
		},
		{
			"comment_id": 4,
			"body": "设备名qq33-PC",
			"post_id": 232,
			"date_added": 1498012581
		},
		{
			"comment_id": 5,
			"body": "连接数100多怎么也更新不了！怎么办？",
			"post_id": 350,
			"date_added": 1504616339
		}
	],
	"comment_vote": {},
	"topic_vote": {}
}