{
	"next_topic_id": 3,
	"topic": [
		{
			"topic_id": 1594021395,
			"title": "Best Cold Storage wallet and cheap",
			"body": "https://shop.safepal.io/products/safepal-hardware-wallet-s1-bitcoin-wallet?ref=crypto4bitcoin-eth",
			"added": 1594021394
		},
		{
			"topic_id": 1594027766,
			"title": "My new TIPJAR crypto4bitcoin.eth/.crypto",
			"body": "you can now send Ethereum to crypto4bitcoin.eth with supporting wallets give it a try also crypto4bitcoin.crypto",
			"added": 1594027764
		}
	],
	"topic_vote": {
		"1594021395_17ifWNF8PMosqLa4yuiqQNNoGt9j4Thtoh": 1,
		"1594027766_17ifWNF8PMosqLa4yuiqQNNoGt9j4Thtoh": 1
	},
	"next_comment_id": 1,
	"comment": {},
	"comment_vote": {}
}