{
	"questions": [
		{
			"question_id": 1517713309884,
			"title": "零网入门常见问题有哪些？",
			"body": "请教",
			"tags": "小白用户,freshhand",
			"date_added": 1517713309884
		},
		{
			"question_id": 1517713537777,
			"title": "我想建立自己的博客，可以从哪儿克隆。",
			"body": "推荐好用的博客",
			"tags": "blog,博客",
			"date_added": 1517713537777,
			"solution_id": 1517713926576,
			"solution_auth_address": "1K7tW4WEbso38uMs4RN3W7GihA6tTqrApz"
		},
		{
			"question_id": 1517714049808,
			"title": "如何在博客中集成Pdf.js系统，让博客可以在线观看pdf文件？",
			"body": "请教",
			"tags": "Pdf.js",
			"date_added": 1517714049808,
			"solution_id": 1517714188581,
			"solution_auth_address": "1K7tW4WEbso38uMs4RN3W7GihA6tTqrApz"
		},
		{
			"question_id": 1517714990111,
			"title": "如何更改别人的网站名?",
			"body": "虽然无法改变网站内容，因为没有私钥。但是我想改变网站名，方便收藏。",
			"tags": "网站名",
			"date_added": 1517714990111
		}
	],
	"answers": [
		{
			"answer_id": 1517713339189,
			"question_id": 1517713309884,
			"question_auth_address": "1K7tW4WEbso38uMs4RN3W7GihA6tTqrApz",
			"body": "常见问题看查看[中文论坛](http://127.0.0.1:43110/NewGFWTalk.bit/?Topic:37_13Z7XxTa7JuFat3KzzMWu3onwM6biLuurJ/+FAQ)\n",
			"date_added": 1517713339189
		},
		{
			"answer_id": 1517713926576,
			"question_id": 1517713537777,
			"question_auth_address": "1K7tW4WEbso38uMs4RN3W7GihA6tTqrApz",
			"body": "推荐三个版本的博客，按照时间顺序来。\n[最初的博客](http://127.0.0.1:43110/Blog.ZeroNetwork.bit/)，也就是开发者最初开发的博客。\n[加强版博客](http://127.0.0.1:43110/19k2nhubaYsDJNPHL6iNs3D2K9Mgj66P4R)增加了博客标签功能，可以按照标签给博客分类或者按照时间给博客分类，但是相对于第一个博客没有方便的在线编辑功能（只能通过markdown语法来改变文字的显示）。\n[改良版博客](http://127.0.0.1:43110/15mSYzsDxzarssqtV1pFPKqoCTaLdjVB2f/)保留了加强版的标签功能，增加了在线编辑功能。同时对手机用户更加友好，并且有[Binchan](http://127.0.0.1:43110/Me.ZeroNetwork.bit/?Profile/1oranGeS2xsKZ4jVsu9SVttzgkYXu4k9v/1AWwhg4EiWAVttfQboJZ4wJfX3WawfJT3h/binchan2@zeroid.bit)在长期更新中，最新版本2018.2.3.",
			"date_added": 1517713926576
		},
		{
			"answer_id": 1517714188581,
			"question_id": 1517714049808,
			"question_auth_address": "1K7tW4WEbso38uMs4RN3W7GihA6tTqrApz",
			"body": "推荐你看看[这篇博客](http://127.0.0.1:43110/12v7UfSjpujeq6xkp8mu64Jt8mEapph8A3/?Post:35)。\n\n它实现了Pdf.js在博客中的集成功能，你可以查看一下该博客的源码或者问问博主。",
			"date_added": 1517714188581
		},
		{
			"answer_id": 1517715154332,
			"question_id": 1517714990111,
			"question_auth_address": "1K7tW4WEbso38uMs4RN3W7GihA6tTqrApz",
			"body": "1只需要打开隐藏按钮，然后点击这是我的网站。(尽管你没有私人钥匙，这也可以打开)\n2然后更改网站名，并保存网站。\n3于是你将看到网站名改变了，但是你不能签名并发布（这意味着只有你看到了改变后的网站名，别人看不到。除非网站拥有者改变了网站名。）",
			"date_added": 1517715154332
		}
	],
	"comments": [
		{
			"comment_id": 1517715169054,
			"reference_type": "a",
			"reference_id": 1517715154332,
			"reference_auth_address": "1K7tW4WEbso38uMs4RN3W7GihA6tTqrApz",
			"body": "GOOd",
			"date_added": 1517715169054
		}
	]
}