{
	"next_topic_id": 1,
	"topic": [],
	"topic_vote": {},
	"next_comment_id": 15,
	"comment": {
		"282_1EZTWytasXcKdiUFnN4KHqAfvg1nwkTkKv": [
			{
				"comment_id": 1,
				"body": "这种东西如何去证实呢？",
				"added": 1498221011
			}
		],
		"296_1EZTWytasXcKdiUFnN4KHqAfvg1nwkTkKv": [
			{
				"comment_id": 2,
				"body": "当年王建林不是就这么干的嘛",
				"added": 1498380405
			},
			{
				"comment_id": 3,
				"body": "王健林不就是这么干的",
				"added": 1498381461
			},
			{
				"comment_id": 4,
				"body": "王健林不就是这么干的",
				"added": 1498381652
			}
		],
		"306_1EZTWytasXcKdiUFnN4KHqAfvg1nwkTkKv": [
			{
				"comment_id": 5,
				"body": "无知者无畏",
				"added": 1498552136
			}
		],
		"305_1EZTWytasXcKdiUFnN4KHqAfvg1nwkTkKv": [
			{
				"comment_id": 6,
				"body": "共产党夺取了政权，这是真的",
				"added": 1498552235
			}
		],
		"352_1EZTWytasXcKdiUFnN4KHqAfvg1nwkTkKv": [
			{
				"comment_id": 7,
				"body": "支持",
				"added": 1499058596
			}
		],
		"395_1EZTWytasXcKdiUFnN4KHqAfvg1nwkTkKv": [
			{
				"comment_id": 8,
				"body": "中国人聪明的很无耻",
				"added": 1499408866
			}
		],
		"466_1EZTWytasXcKdiUFnN4KHqAfvg1nwkTkKv": [
			{
				"comment_id": 9,
				"body": "你们还真拿中国政府说的话等回事儿啊，连屁都不如",
				"added": 1500267564
			}
		],
		"459_1EZTWytasXcKdiUFnN4KHqAfvg1nwkTkKv": [
			{
				"comment_id": 10,
				"body": "R.I.P",
				"added": 1500267697
			}
		],
		"463_1EZTWytasXcKdiUFnN4KHqAfvg1nwkTkKv": [
			{
				"comment_id": 11,
				"body": "共产党嘴里喷出来的都是粪",
				"added": 1500267807
			}
		],
		"461_1EZTWytasXcKdiUFnN4KHqAfvg1nwkTkKv": [
			{
				"comment_id": 12,
				"body": "R.I.P",
				"added": 1500268004
			}
		],
		"460_1EZTWytasXcKdiUFnN4KHqAfvg1nwkTkKv": [
			{
				"comment_id": 13,
				"body": "本质",
				"added": 1500268179
			}
		],
		"475_1EZTWytasXcKdiUFnN4KHqAfvg1nwkTkKv": [
			{
				"comment_id": 14,
				"body": "我们则继续活着",
				"added": 1500279683
			}
		]
	},
	"comment_vote": {}
}