{
	"next_comment_id": 10,
	"comment": [
		{
			"comment_id": 1,
			"body": "google和github用了好久了，就是编程语言只会C",
			"post_id": 21,
			"date_added": 1476958625
		},
		{
			"comment_id": 2,
			"body": "其实用optional files的话不用在意大小，因为用户不访问的话就不会加载",
			"post_id": 22,
			"date_added": 1476958737
		},
		{
			"comment_id": 4,
			"body": "> [91](#comment_12_1L3M5zYC5UDEtZn3X8gbYTTecRDH5nZJMf): 我的小黄网浏览量稳定下来了，不过zeronet关键还是形成了一个闭环，来来去去其实就是这几十个程序员在玩，吸引不来外来人员访问。http://127.0.0.1:43110/1PKDXAgCBR77JBwjir4cjjXt2hwSpw78bs/?Home\n\n我这不是来了嘛，我打算用这个把一大堆墙外的资料搬到墙内",
			"post_id": 19,
			"date_added": 1476968660
		},
		{
			"comment_id": 5,
			"body": "> [91](#comment_12_1L3M5zYC5UDEtZn3X8gbYTTecRDH5nZJMf): 我的小黄网浏览量稳定下来了，不过zeronet关键还是形成了一个闭环，来来去去其实就是这几十个程序员在玩，吸引不来外来人员访问。http://127.0.0.1:43110/1PKDXAgCBR77JBwjir4cjjXt2hwSpw78bs/?Home\n\n原来这个小黄网是你建的，谢谢哈。我也用NullChan做了个小黄网，专门放CD的黄图http://127.0.0.1:43110/1fu1iNKkkCZRwD37N6oB6mv1oHWiPVUCf/",
			"post_id": 19,
			"date_added": 1476968808
		},
		{
			"comment_id": 6,
			"body": "人气不高说明审查还不严，要是哪天微博严格限制政治相关话题，GFWTALK的政治版几天内就会被骂政府的淹没.而zeronet恰恰是对抗审查的有效手段",
			"post_id": 9,
			"date_added": 1476969613
		},
		{
			"comment_id": 7,
			"body": "> [cxgreat2014](#comment_6_18hidquEH7k6Dnn5MDd4zJFJ2cTUF22wk2): 没跳，并在控制台显示以下错误：Ignored call to 'alert()'. The document is sandboxed, and the 'allow-modals' keyword is not set.\n\n原来是屏蔽了啊",
			"post_id": 7,
			"date_added": 1477908934
		},
		{
			"comment_id": 8,
			"body": "现在有些zeronet网站已经集成了webtorrent，就是没办法做到边下边播",
			"post_id": 20,
			"date_added": 1477924604
		},
		{
			"comment_id": 9,
			"body": "> [deep](#comment_8_1A5Uw4pejzgKx4c3yZkz8whBcqMaypp1Wo): 土共真是作死，go语言的官网也封了。按牠们的理论，生产关系阻碍生产力发展就是反动势力。\n\n现在的TG不就跟当年的国民党差不多了吗",
			"post_id": 20,
			"date_added": 1478410592
		}
	],
	"comment_vote": {},
	"topic_vote": {}
}