{
	"title": "第五維空間",
	"description": "love miku  and interesting",
	"links": "*   这是一个刚刚接触零网的人搞的博客，可能真的很简陋，不过没问题我会慢慢学习怎么弄好它。\n*   [Source code](https://github.com/HelloZeroNet)",
	"next_post_id": 55,
	"demo": false,
	"modified": 1598187772,
	"post": [
		{
			"post_id": 54,
			"title": "懶惰的一天",
			"date_published": 1582130520.972,
			"body": "實際上博客沒死，還在管理的，只是很懶很懶"
		},
		{
			"post_id": 53,
			"title": "复活一下",
			"date_published": 1557683472.748,
			"body": "![IMG_1229.JPG (0x0)](data/img/post_53_IMG_1229.JPG)"
		},
		{
			"post_id": 52,
			"title": "又很久没连接",
			"date_published": 1534960174.245,
			"body": "xxxx"
		},
		{
			"post_id": 49,
			"title": "lalala",
			"date_published": 1519930037.237,
			"body": "![](data:,)"
		},
		{
			"post_id": 44,
			"title": "适度更新",
			"date_published": 1511876393.814,
			"body": "貌似图片又没法上传"
		},
		{
			"post_id": 43,
			"title": "白茫茫",
			"date_published": 1510146668.096,
			"body": "看来是需要研究下怎么改一改这个网页了，老是用默认模板，感觉不咋地"
		},
		{
			"post_id": 42,
			"title": "突然节点多起来",
			"date_published": 1509209149.749,
			"body": "我天天都在做种"
		},
		{
			"post_id": 41,
			"title": "啦啦啦啦",
			"date_published": 1508590763.743,
			"body": "19big 结束拉"
		},
		{
			"post_id": 40,
			"title": "好像忘记放图",
			"date_published": 1508251732.959,
			"body": "本来我是准备好的，结果忘记了\n\n![photo_2017-10-17_22-49-40.jpg (0x0)](data/img/post_40_photo_2017-10-17_22-49-40.jpg)"
		},
		{
			"post_id": 39,
			"title": "就是这样\n",
			"date_published": 1507830435.953,
			"body": "又一段时间没上来，不过种子是有在做"
		},
		{
			"post_id": 38,
			"title": "哇，初音10周年我都忘记更新",
			"date_published": 1504379710.673,
			"body": "![IMG_2499.JPG (0x0)](data/img/post_38_IMG_2499.JPG)"
		},
		{
			"post_id": 37,
			"title": "先膜一阵子",
			"date_published": 1503337434.185,
			"body": "![photo_2017-08-22_01-43-16.jpg (0x0)](data/img/post_37_photo_2017-08-22_01-43-16.jpg)"
		},
		{
			"post_id": 35,
			"title": "-1s",
			"date_published": 1501770963.518,
			"body": "![photo_2017-08-03_22-38-56.jpg (0x0)](data/img/post_35_photo_2017-08-03_22-38-56.jpg)"
		},
		{
			"post_id": 34,
			"title": "搞点趣图再膜一膜会不会好些",
			"date_published": 1501770899.78,
			"body": "![photo_2017-08-03_22-34-50.jpg (0x0)](data/img/post_34_photo_2017-08-03_22-34-50.jpg)"
		},
		{
			"post_id": 32,
			"title": "30人",
			"date_published": 1501420687.684,
			"body": "看起来多人了起来，是不是要多更新下"
		},
		{
			"post_id": 31,
			"title": "随便聊聊吧",
			"date_published": 1499873628.137,
			"body": "接触零网的时候是去年的7月份的样子，如今已经有一年了，我基本上是每天挂着后台，很少经常探索，可能是因为内容还不够活跃的缘故，慢慢来吧，可能接下来用的人就越来越多了，毕竟某些程度上来说，这玩意可以提供局域网环境内另外一个天地，我是真心希望有越来越多的人来用这个软件，这样节点到处都是，整个网络的稳定性就大大的增强。\n\n可能接下来一段时间我就平时不只是更新初音的图片了，看到好图就放上来吧。"
		},
		{
			"post_id": 29,
			"title": "哇，我是不是应该多更新下",
			"date_published": 1499260351.868,
			"body": "真的挺长时间没弄，天天挂着ZeroNet，就是没点进去打开一下我这个网页，不知道的可能以为弃坑了"
		},
		{
			"post_id": 28,
			"title": "时隔一个月",
			"date_published": 1496342528.544,
			"body": "最近好忙，都忘记这里了"
		},
		{
			"post_id": 27,
			"title": "貌似终于可以放图片了",
			"date_published": 1493397798.74,
			"body": "![photo_2017-03-15_19-00-22.jpg (0x0)](data/img/post_27_photo_2017-03-15_19-00-22.jpg)"
		},
		{
			"post_id": 26,
			"title": "又找到一些图",
			"date_published": 1490967925.749,
			"body": "不知道为啥，放图片上来的时候图片会挂掉，难道我打开方式不对，好吧，过几天再更新吧"
		},
		{
			"post_id": 24,
			"title": "在G+上面看到的",
			"date_published": 1489575630.258,
			"body": "![photo_2017-03-15_19-00-27.jpg (1280x629)](data/img/post_24_photo_2017-03-15_19-00-27.jpg)​​​​​​​"
		},
		{
			"post_id": 23,
			"title": "现在的手机壁纸",
			"date_published": 1488288820.285,
			"body": "![photo_2017-02-28_21-54-09.jpg (905x1280)](data/img/post_23_photo_2017-02-28_21-54-09.jpg)​​​​​​​"
		},
		{
			"post_id": 22,
			"title": "2017年2月22日 ",
			"date_published": 1487692954.168,
			"body": "又有很多天没管理...."
		},
		{
			"post_id": 21,
			"title": "新年好",
			"date_published": 1485961838.261,
			"body": "我居然忘记更新"
		},
		{
			"post_id": 20,
			"title": "另外一只",
			"date_published": 1485149784.915,
			"body": "![IMG_0486.JPG (1200x839)](data/img/post_20_IMG_0486.JPG)​​​​​​​"
		},
		{
			"post_id": 19,
			"title": "我在G+找到的星空miku",
			"date_published": 1484936564.352,
			"body": "![IMG_0484.JPG (1200x787)](data/img/post_19_IMG_0484.JPG)​​​​​​​\n\n作者不明，应该是p站的"
		},
		{
			"post_id": 18,
			"title": "2017年1月19日",
			"date_published": 1484830353.578,
			"body": "![pixiv55588225.jpg (636x900)](data/img/post_18_pixiv55588225.jpg)​​​​​​​"
		},
		{
			"post_id": 17,
			"title": "再来",
			"date_published": 1484708329.924,
			"body": "![pixiv55922552_0.jpg (1200x900)](data/img/post_17_pixiv55922552_0.jpg)​​​​​​​"
		},
		{
			"post_id": 16,
			"title": "2017年1月12日",
			"date_published": 1484229614.465,
			"body": "![pixiv55773272_2.jpg (610x900)](data/img/post_16_pixiv55773272_2.jpg)​​​​​​​"
		},
		{
			"post_id": 15,
			"title": "我继续放图",
			"date_published": 1484041686.846,
			"body": "暂时没有想到这个博客要拿来干什么，继续放图\n\n![pixiv60541651.jpg (552x900)](data/img/post_15_pixiv60541651.jpg)"
		},
		{
			"post_id": 13,
			"title": "啦啦啦",
			"date_published": 1483705449.794,
			"body": "![photo_2017-01-06_20-28-26.jpg (1280x720)](data/img/post_13_photo_2017-01-06_20-28-26.jpg)​​​​​​​"
		},
		{
			"post_id": 12,
			"title": "什么？图片不够大，放大不够清晰？ 其实是有黑科技的",
			"date_published": 1483643016.54,
			"body": "把你喜欢的动漫风格的图片放到这个网站：[http://waifu2x.udp.jp（明网注意）](http://waifu2x.udp.jp/index.zh-CN.html) 它叫 waifu2x（老婆两倍大）它可以将图片“无损”放大两倍，并且有降噪功能，可以达到下面的效果。\n\n![slide.jpg (400x900)](data/img/post_12_slide.jpg)\n\n它的原理是一种人工智能的神经网络算法，相当于让计算机重新画一幅高分辨率的画，另外这个项目是开源的，也有pc版本的放大，大家可以去[GitHub（明网注意）](https://github.com/nagadomi/waifu2x)看看。"
		},
		{
			"post_id": 11,
			"title": "我拿来做了很长时间的锁屏壁纸",
			"date_published": 1483514185.01,
			"body": "![pixiv58984528_0.jpg (636x900)](data/img/post_11_pixiv58984528_0.jpg)![pixiv58984528_1.jpg (636x900)](data/img/post_11_pixiv58984528_1.jpg)\n\n来源p站，版权原作者所有\n\nヤクソク | あさひ＠KYD #pixiv [http://www.pixiv.net/member_illust.php?illust_id=58984528&mode=medium （明网注意）](ヤクソク | あさひ＠KYD #pixiv http://www.pixiv.net/member_illust.php?illust_id=58984528&mode=medium)"
		},
		{
			"post_id": 9,
			"title": "2017的星空miku",
			"date_published": 1483466443.853,
			"body": "![pixiv59025444_0.jpg (558x900)](data/img/post_9_pixiv59025444_0.jpg)​​​​​​​\n\n是不是应该贴上p站id，不过应该很好找，版权属作者所有"
		},
		{
			"post_id": 8,
			"title": "放几张图片",
			"date_published": 1483438136.535,
			"body": "![__19.jpg (637x900)](data/img/post_8___19.jpg)​​​​​​​"
		},
		{
			"post_id": 7,
			"title": "放张图试试先",
			"date_published": 1483416764.862,
			"body": "![__20.jpg (663x900)](data/img/post_7___20.jpg)​​​​​​​"
		},
		{
			"post_id": 6,
			"title": "成功建立第一个属于我自己的零网博客",
			"date_published": 1483416555.206,
			"body": "貌似现在有5个节点了"
		},
		{
			"post_id": 5,
			"title": "4523466456463342534",
			"date_published": 1483373774.275,
			"body": "1321312314512354132128645542144323448386763537342"
		},
		{
			"post_id": 4,
			"title": "233",
			"date_published": 1483373235.771,
			"body": "再次测试"
		},
		{
			"post_id": 3,
			"title": "嘿嘿嘿",
			"date_published": 1483373129.251,
			"body": "测试发布"
		},
		{
			"post_id": 2,
			"title": "2017年1月2日",
			"date_published": 1483371892.939,
			"body": "尝试建立一个零网博客"
		},
		{
			"post_id": 1,
			"title": "Congratulations!",
			"date_published": 1433033779.604,
			"body": "Your zeronet blog has been successfully created!"
		}
	]
}