{
	"next_post_id": 7,
	"next_comment_id": 7,
	"next_follow_id": 3,
	"avatar": "generate",
	"user_name": "Christina Rosa",
	"hub": "1MoonP8t4rk9QamBUPh5Aspkwa1Xhf5ux2",
	"intro": "The secret grey hat， watching any time anywhere.\n\nContact:\nchristina.rosasec@protonmail.com\nOr send by zeromail (receive only,please write your protonmail address for reply)",
	"post": [
		{
			"post_id": 1,
			"date_added": 1577815808,
			"body": "Hello ZeroMe!"
		},
		{
			"post_id": 1577816190,
			"body": "Hi everyone, I had a account for a previous time but I failed for recovery so I create new one.",
			"date_added": 1577816188
		},
		{
			"post_id": 1577816238,
			"body": "I am still call Christina Rosa",
			"date_added": 1577816235
		},
		{
			"post_id": 1577990462,
			"body": "唉，在手機上內網，可是zero mail不能用…",
			"date_added": 1577990458
		},
		{
			"post_id": 1578038064,
			"body": "我發現除了論壇還有這裡以外，其他很多功能也無法使用…zeromail原本很想發出去，可是打用戶名也打不了進去，這以後這個只能接收信息了。不過如果有興趣給資訊或者寫信給我的話，可以發個protonmail哦",
			"date_added": 1578038059
		},
		{
			"post_id": 1578057953,
			"body": "What problem about it?\nHelp!",
			"date_added": 1578057947,
			"meta": "{\"img\":\"323,700,eeeebbfffbbbdddedd,00000122220000023222222222202220022244022404225000\"}"
		}
	],
	"post_like": {},
	"comment": [
		{
			"comment_id": 1,
			"body": "Er...it really disgusted",
			"post_uri": "1JTAovubGopbQ7wN5xnjJzQ1jsRiA1d8pt_1577775560",
			"date_added": 1577828620
		},
		{
			"comment_id": 2,
			"body": "你有任何資料嗎？",
			"post_uri": "13KwoYsPQsMpKL27znfVicYa9FSPnEX73F_1577686127",
			"date_added": 1577828670
		},
		{
			"comment_id": 3,
			"body": "@1bfqutudhtexlka:  it really suck.",
			"post_uri": "15Jmu7DkbxqtQ6mFhu6gLT1pbiMM55oywF_1578057953",
			"date_added": 1578066407
		},
		{
			"comment_id": 4,
			"body": "@O66p: 也知道，可是 就是寫不進去",
			"post_uri": "15Jmu7DkbxqtQ6mFhu6gLT1pbiMM55oywF_1578038064",
			"date_added": 1578136497
		},
		{
			"comment_id": 5,
			"body": "@Git Center:  I am using xiaomi",
			"post_uri": "15Jmu7DkbxqtQ6mFhu6gLT1pbiMM55oywF_1578057953",
			"date_added": 1578213788
		},
		{
			"comment_id": 6,
			"body": "@Git Center: yup",
			"post_uri": "15Jmu7DkbxqtQ6mFhu6gLT1pbiMM55oywF_1578057953",
			"date_added": 1578559094
		}
	],
	"follow": [
		{
			"follow_id": 1,
			"hub": "1MoonP8t4rk9QamBUPh5Aspkwa1Xhf5ux2",
			"auth_address": "13EcmTsfiR4mFvepkVNHgFgLDSNCrbe4PP",
			"user_name": "珏龖",
			"date_added": 1577827292
		},
		{
			"follow_id": 2,
			"hub": "1SunAWK2VUT9GQK32MpwRfFPVgcBSJN9a",
			"auth_address": "1Cy3ntkN2GN9MH6EaW6eHpi4YoRS2nK5Di",
			"user_name": "Git Center",
			"date_added": 1578136592
		}
	]
}