{
	"user": [
		{
			"user_id": "181Ky8Nr6q2YsEGGDdgUrkphqBimqP57p",
			"user_name": "Cmdou80BLAOHG@zv.anonymous",
			"added": 1545403160164
		}
	],
	"next_user_id": 2,
	"comment": [
		{
			"comment_id": "181Ky8Nr6q2YsEGGDdgUrkphqBimqP57pcomment1",
			"body": "Yes, use different port<br>",
			"body_p": "Yes, use different port",
			"topic_id": "1Q3kBHBtHb4gJHUjUQQ9eLHyMJ6Kz47yJttopic3",
			"user_id": "Cmdou80BLAOHG@zv.anonymous",
			"comment_parent_id": 0,
			"added": 1545403273762
		}
	],
	"next_comment_id": 2,
	"comment_vote": [
		{
			"user_id": "Cmdou80BLAOHG@zv.anonymous",
			"vote": 1,
			"added": 1545403402348,
			"comment_vote_id": "181Ky8Nr6q2YsEGGDdgUrkphqBimqP57pvt1",
			"comment_id": "1PYNb5qEDeoxswHtAFHDdLLLSPWGUc4f68comment7"
		}
	],
	"next_comment_vote_id": 2
}